banner_seokxkyu/__init__.py
banner_seokxkyu/banner.py
banner_seokxkyu-0.3.0.dist-info/METADATA
banner_seokxkyu-0.3.0.dist-info/WHEEL
banner_seokxkyu-0.3.0.dist-info/entry_points.txt
banner_seokxkyu-0.3.0.dist-info/top_level.txt
banner_seokxkyu-0.3.0.dist-info/RECORD
