Metadata-Version: 2.1
Name: banner_seokxkyu
Version: 0.3.0
Summary: Banner Output Program
Author-email: Seokxkyu <kyuseok000@gmail.com>
License: MIT
Project-URL: Homepage, https://github.com/Seokxkyu/banner_seokxkyu
Project-URL: Issues, https://github.com/Seokxkyu/banner_seokxkyu/issues
Requires-Python: >=3.9
Requires-Dist: pyfiglet >=1.0.2
